Metadata-Version: 2.1
Name: odoo-addon-sale_loyalty_criteria_multi_product
Version: 16.0.1.0.0.5
Summary: Allows to set as promotion criteria multi-product conditions
Home-page: https://github.com/OCA/sale-promotion
Author: Tecnativa, Odoo Community Association (OCA)
Author-email: support@odoo-community.org
License: AGPL-3
Classifier: Programming Language :: Python
Classifier: Framework :: Odoo
Classifier: Framework :: Odoo :: 16.0
Classifier: License :: OSI Approved :: GNU Affero General Public License v3
Classifier: Development Status :: 5 - Production/Stable
Requires-Python: >=3.10
Requires-Dist: odoo-addon-loyalty-criteria-multi-product <16.1dev,>=16.0dev
Requires-Dist: odoo <16.1dev,>=16.0a
